mcp_edit_math.py
mcp_edit_math-1.5.0.dist-info/METADATA
mcp_edit_math-1.5.0.dist-info/WHEEL
mcp_edit_math-1.5.0.dist-info/entry_points.txt
mcp_edit_math-1.5.0.dist-info/top_level.txt
mcp_edit_math-1.5.0.dist-info/RECORD
