Metadata-Version: 2.4
Name: mcp-edit-math
Version: 1.5.0
Summary: An implementation of the Edit Approval State Machine (EASM) (MCP Server)
Author-email: Annenkov Yuriy <yannenkovkraft@gmail.com>
Project-URL: Homepage, https://github.com/yrannkv/mcp-edit-math
Project-URL: Repository, https://github.com/yrannkv/mcp-edit-math
Keywords: mcp,ai,llm,security,tree-sitter
Classifier: Development Status :: 4 - Beta
Classifier: Intended Audience :: Developers
Classifier: License :: OSI Approved :: Apache Software License
Classifier: Programming Language :: Python :: 3.10
Classifier: Programming Language :: Python :: 3.11
Classifier: Programming Language :: Python :: 3.12
Requires-Python: >=3.10
Requires-Dist: mcp
Requires-Dist: tree-sitter==0.21.3
Requires-Dist: tree-sitter-javascript==0.21.0
Requires-Dist: tree-sitter-typescript==0.21.0
Requires-Dist: tree-sitter-html==0.20.3
